{

    "_id": "1000",
    "SourceForgeId": "51507be227184610346870fd",
    "projectName": "discrialign",
    "projectURL": "http://sourceforge.net/projects/discrialign",
    "projectrestAPIURL": "ttp://sourceforge.net/rest/p/discrialign",
    "creationDate": "2008-09-23",
    "externalHomepage": "http://discrialign.sourceforge.net",
    "movedToUrl": "",
    "name": "DiscriAlign",
    "preferredSupportTool": "",
    "preferredSupportUrl": "",
    "_private": false,
    "shortDescription": "DiscriAlign implements a novel algorithm that aligns a set of biological interaction networks.It identifies both functionally conserved and dissimilar regions. \r\n",
    "shortname": "discrialign",
    "status": "active",
    "summary": "",
    "url": "http://sourceforge.net/p/discrialign/",
    "videoUrl": "",
    "codeFiles": [{
        "fileName": "Testing",
        "fileType": ".java"
    }, {
        "fileName": "make",
        "fileType": ".java"
    }],
    "developers": [{
        "name": "Seah Boon Siew",
        "url": "http://sourceforge.net/u/quainter/",
        "username": "quainter",
        "userprofile": {
            "availability": [],
            "joined": "2008-09-23 03:45:21",
            "localization": {},
            "name": "Seah Boon Siew",
            "projects": [{
                "last_updated": "2013-03-25 16:31:34.730000",
                "name": "DiscriAlign",
                "summary": "",
                "url": "/p/discrialign/"
            }],
            "sex": "Unknown",
            "skills": [],
            "telnumbers": [],
            "username": "quainter",
            "webpages": []
        }
    }],
    "tools": [{
        "label": "Summary",
        "mount_point": "summary",
        "name": "summary",
        "sourceforgeGroupId": 240402
    }, {
        "label": "Support",
        "mount_point": "support",
        "name": "support",
        "sourceforgeGroupId": -1
    }, {
        "label": "Reviews",
        "mount_point": "reviews",
        "name": "reviews",
        "sourceforgeGroupId": -1
    }, {
        "label": "Wiki",
        "mount_point": "wiki",
        "name": "wiki",
        "sourceforgeGroupId": -1,
        "mount_point_data": {
            "pages": [
                "Home"
            ]
        }
    }, {
        "label": "Files",
        "mount_point": "files",
        "name": "files",
        "sourceforgeGroupId": -1,
        "mount_point_data": {
            "pages": [
                "Home"
            ]
        }
    }],
    "screenshots": [],
    "socialnetworks": [],
    "labels": [],
    "categories": {
        "audience": [{
            "fullname": "Science/Research",
            "fullpath": "Intended Audience :: by Industry or Sector :: Science/Research",
            "id": 367,
            "shortname": "scienceresearch"
        }],
        "database": [{
            "id": -1
        }],
        "developmentstatus": [{
            "fullname": "2 - Pre-Alpha",
            "fullpath": "Development Status :: 2 - Pre-Alpha",
            "id": 8,
            "shortname": "prealpha"
        }],
        "environment": [{
            "fullname": "Eclipse",
            "fullpath": "User Interface :: Plugins :: Eclipse",
            "id": 583,
            "shortname": "eclipse_plugins"
        }],
        "language": [{
            "fullname": "Java",
            "fullpath": "Programming Language :: Java",
            "id": 198,
            "shortname": "java"
        }],
        "license": [{
            "fullname": "BSD License",
            "fullpath": "License :: OSI-Approved Open Source :: BSD License",
            "id": 187,
            "shortname": "bsd"
        }],
        "os": [{
            "id": -1
        }],
        "topic": [{
            "fullname": "Visualization",
            "fullpath": "Topic :: Scientific/Engineering :: Visualization",
            "id": 135,
            "shortname": "visualization"
        }, {
            "fullname": "Information Analysis",
            "fullpath": "Topic :: Scientific/Engineering :: Information Analysis",
            "id": 385,
            "shortname": "informationanalysis"
        }],
        "translation": [{
            "id": -1
        }]
    }
}